README.md
setup.py
safecustody_sdk/__init__.py
safecustody_sdk/error.py
safecustody_sdk/example.py
safecustody_sdk/request.py
safecustody_sdk/route.py
safecustody_sdk/sdk.py
safecustody_sdk/user.py
safecustody_sdk.egg-info/PKG-INFO
safecustody_sdk.egg-info/SOURCES.txt
safecustody_sdk.egg-info/dependency_links.txt
safecustody_sdk.egg-info/top_level.txt